pasta_eln/__init__.py
pasta_eln/fixedStringsJson.py
pasta_eln/gui.py
pasta_eln/installationTools.py
pasta_eln/miscTools.py
pasta_eln/tools.py
pasta_eln/AddOns/README.md
pasta_eln/AddOns/definition_autofill.py
pasta_eln/AddOns/extractor_csv.py
pasta_eln/AddOns/extractor_jpeg.py
pasta_eln/AddOns/extractor_jpg.py
pasta_eln/AddOns/extractor_json.py
pasta_eln/AddOns/extractor_log.py
pasta_eln/AddOns/extractor_md.py
pasta_eln/AddOns/extractor_png.py
pasta_eln/AddOns/extractor_py.py
pasta_eln/AddOns/extractor_tif.py
pasta_eln/AddOns/extractor_tsv.py
pasta_eln/AddOns/form_auto.py
pasta_eln/AddOns/project_html_report.py
pasta_eln/AddOns/project_importCSV.py
pasta_eln/AddOns/project_sort_children.py
pasta_eln/AddOns/table_plot.py
pasta_eln/AddOns/table_plotData.py
pasta_eln/Resources/ExampleMeasurements/example.tif
pasta_eln/Resources/ExampleMeasurements/simple.csv
pasta_eln/Resources/ExampleMeasurements/simple.png
pasta_eln/Resources/ExampleMeasurements/story.odt
pasta_eln/Resources/ExampleWorkflows/procedure.md
pasta_eln/Resources/ExampleWorkflows/worklog.log
pasta_eln/Resources/ExampleWorkflows/workplan.py
pasta_eln/Resources/Icons/favicon64.ico
pasta_eln/Resources/Icons/favicon64.png
pasta_eln/Resources/Icons/ols.png
pasta_eln/Resources/Icons/pasta512.png
pasta_eln/Resources/Icons/tib.png
pasta_eln/Resources/Icons/wikidata.png
pasta_eln/Resources/Icons/wikipedia.png
pasta_eln/UI/__init__.py
pasta_eln/UI/_contextMenu.py
pasta_eln/UI/body.py
pasta_eln/UI/details.py
pasta_eln/UI/docTypes.py
pasta_eln/UI/form.py
pasta_eln/UI/gallery.py
pasta_eln/UI/guiCommunicate.py
pasta_eln/UI/guiStyle.py
pasta_eln/UI/mainWindow.py
pasta_eln/UI/messageDialog.py
pasta_eln/UI/palette.py
pasta_eln/UI/project.py
pasta_eln/UI/projectLeafRenderer.py
pasta_eln/UI/projectTreeView.py
pasta_eln/UI/sidebar.py
pasta_eln/UI/table.py
pasta_eln/UI/tableFilterManager.py
pasta_eln/UI/tableHeader.py
pasta_eln/UI/textEditor.py
pasta_eln/UI/waitDialog.py
pasta_eln/UI/config/__init__.py
pasta_eln-3.2.2.dist-info/licenses/LICENSE
pasta_eln-3.2.2.dist-info/METADATA
pasta_eln-3.2.2.dist-info/WHEEL
pasta_eln-3.2.2.dist-info/entry_points.txt
pasta_eln-3.2.2.dist-info/top_level.txt
pasta_eln-3.2.2.dist-info/RECORD
