Metadata-Version: 2.4
Name: pasta_eln
Version: 3.2.2
Summary: The favorite ELN for experimental scientists
Home-page: https://pasta-eln.github.io/
Author: The PASTA-ELN Team and Steffen Brinckmann
Author-email: sbrinckm@gmail.com
License: MIT
Classifier: Programming Language :: Python
Classifier: License :: OSI Approved :: BSD License
Classifier: Programming Language :: Python :: 3
Requires-Python: >=3.10
License-File: LICENSE
Requires-Dist: anytree
Requires-Dist: cryptography
Requires-Dist: matplotlib
Requires-Dist: pandas
Requires-Dist: Pillow
Requires-Dist: pyside6
Requires-Dist: qrcode
Requires-Dist: QtAwesome
Requires-Dist: qt-material
Requires-Dist: pypiwin32; platform_system == "Windows"
Requires-Dist: requests
Requires-Dist: win-unicode-console; platform_system == "Windows"
Requires-Dist: winshell; platform_system == "Windows"
Provides-Extra: devel
Requires-Dist: sphinx; extra == "devel"
Dynamic: license-file
